OneIoT/Device.py
OneIoT/DeviceManager.py
OneIoT/__init__.py
OneIoT/setupOLD.py
OneIoT/test.py
oneiot/Device.py
oneiot/DeviceManager.py
oneiot/EventBus.py
oneiot/__init__.py
oneiot/setupOLD.py
oneiot/test.py
oneiot-0.1.0.dist-info/LICENSE
oneiot-0.1.0.dist-info/METADATA
oneiot-0.1.0.dist-info/WHEEL
oneiot-0.1.0.dist-info/top_level.txt
oneiot-0.1.0.dist-info/RECORD
