Metadata-Version: 2.1
Name: oneiot
Version: 0.1.0
Summary: OneIoT
Home-page: https://github.com/lirwin3007/OneIoT
Author: Louis Irwin
Author-email: coding@louisirwin.co.uk
License: UNKNOWN
Platform: UNKNOWN
Requires-Python: >=3.6
